{"Player":{"coins":8128,"blood":0,"pieces":[{"name":"Rother","uniqueId":11,"pieceType":3,"attack":1,"defense":1,"support":1,"color":0,"posX":0,"posY":0,"abilities":[]},{"name":"Baldegilde","uniqueId":12,"pieceType":1,"attack":1,"defense":1,"support":1,"color":0,"posX":1,"posY":0,"abilities":[]},{"name":"Sicleholde","uniqueId":13,"pieceType":2,"attack":1,"defense":1,"support":1,"color":0,"posX":2,"posY":0,"abilities":[]},{"name":"Nadaltrude","uniqueId":14,"pieceType":4,"attack":1,"defense":1,"support":1,"color":0,"posX":3,"posY":0,"abilities":[{"abilityName":"Noble Ashes","abilityDescription":"+1 to all stats for each owned ranked (non-pawn) piece below 8"}]},{"name":"Fredhelm","uniqueId":15,"pieceType":5,"attack":1,"defense":1,"support":1,"color":0,"posX":4,"posY":0,"abilities":[]},{"name":"Dewnes","uniqueId":16,"pieceType":2,"attack":1,"defense":1,"support":1,"color":0,"posX":5,"posY":0,"abilities":[]},{"name":"Omnebon","uniqueId":17,"pieceType":1,"attack":1,"defense":1,"support":1,"color":0,"posX":6,"posY":0,"abilities":[]},{"name":"Noto","uniqueId":18,"pieceType":3,"attack":6,"defense":6,"support":6,"color":0,"posX":7,"posY":0,"abilities":[{"abilityName":"Soul Bond","abilityDescription":"+5 to all stat for each other soul bonded piece, when any soul bonded piece is captured, all are decimated"}]},{"name":"Bonanata","uniqueId":19,"pieceType":0,"attack":1,"defense":1,"support":1,"color":0,"posX":0,"posY":1,"abilities":[{"abilityName":"Critical Blow","abilityDescription":"10% chance of x2 attack"},{"abilityName":"Spectral Stride","abilityDescription":"Can move through it's own pieces according to it's typical movement"}]},{"name":"Dagmar","uniqueId":20,"pieceType":0,"attack":1,"defense":1,"support":1,"color":0,"posX":1,"posY":1,"abilities":[]},{"name":"Uriah","uniqueId":21,"pieceType":0,"attack":1,"defense":1,"support":1,"color":0,"posX":2,"posY":1,"abilities":[]},{"name":"Meingold","uniqueId":22,"pieceType":0,"attack":1,"defense":1,"support":1,"color":0,"posX":3,"posY":1,"abilities":[]},{"name":"Driwethen","uniqueId":23,"pieceType":0,"attack":6,"defense":6,"support":6,"color":0,"posX":4,"posY":1,"abilities":[{"abilityName":"Scout <sprite=\"WhitePawn\" name=\"WhitePawn\">","abilityDescription":"Moves like queen, attacks & supports like pawn"},{"abilityName":"Soul Bond","abilityDescription":"+5 to all stat for each other soul bonded piece, when any soul bonded piece is captured, all are decimated"}]},{"name":"Sylvester","uniqueId":24,"pieceType":0,"attack":1,"defense":1,"support":1,"color":0,"posX":5,"posY":1,"abilities":[]},{"name":"Christian","uniqueId":25,"pieceType":0,"attack":1,"defense":1,"support":1,"color":0,"posX":6,"posY":1,"abilities":[]},{"name":"Sebastiana","uniqueId":26,"pieceType":0,"attack":1,"defense":1,"support":1,"color":0,"posX":7,"posY":1,"abilities":[]}]},"State":3,"Level":2,"MapNodes":[{"nodeName":"Start Node","isCompleted":false,"connectedNodes":["Node 0","SecondNode 10"],"nodeType":0,"enemyType":0,"encounterType":0,"localX":-835.92,"localY":0.0,"isCurrentNode":false,"color":{"r":1.0,"g":1.0,"b":1.0,"a":1.0}},{"nodeName":"Node 0","isCompleted":false,"connectedNodes":["Node 1"],"nodeType":0,"enemyType":4,"encounterType":0,"localX":-680.399963,"localY":65.01157,"isCurrentNode":false,"color":{"r":1.0,"g":1.0,"b":1.0,"a":1.0}},{"nodeName":"Node 1","isCompleted":false,"connectedNodes":["Node 2","SecondNode 12"],"nodeType":0,"enemyType":6,"encounterType":0,"localX":-524.879944,"localY":183.383331,"isCurrentNode":false,"color":{"r":1.0,"g":1.0,"b":1.0,"a":1.0}},{"nodeName":"Node 2","isCompleted":false,"connectedNodes":["Node 3"],"nodeType":0,"enemyType":0,"encounterType":0,"localX":-369.36,"localY":58.7150421,"isCurrentNode":false,"color":{"r":1.0,"g":1.0,"b":1.0,"a":1.0}},{"nodeName":"Node 3","isCompleted":false,"connectedNodes":["Node 4"],"nodeType":0,"enemyType":0,"encounterType":0,"localX":-213.84,"localY":-52.60527,"isCurrentNode":false,"color":{"r":1.0,"g":1.0,"b":1.0,"a":1.0}},{"nodeName":"Node 4","isCompleted":false,"connectedNodes":["Node 5","SecondNode 15"],"nodeType":0,"enemyType":4,"encounterType":0,"localX":-58.3199959,"localY":-175.4881,"isCurrentNode":false,"color":{"r":1.0,"g":1.0,"b":1.0,"a":1.0}},{"nodeName":"Node 5","isCompleted":false,"connectedNodes":["Node 6","EncounterFirst Path Node5"],"nodeType":0,"enemyType":6,"encounterType":0,"localX":97.19999,"localY":-170.107376,"isCurrentNode":false,"color":{"r":1.0,"g":1.0,"b":1.0,"a":1.0}},{"nodeName":"Node 6","isCompleted":false,"connectedNodes":["Node 7"],"nodeType":0,"enemyType":1,"encounterType":0,"localX":252.719986,"localY":-160.593811,"isCurrentNode":false,"color":{"r":1.0,"g":1.0,"b":1.0,"a":1.0}},{"nodeName":"Node 7","isCompleted":false,"connectedNodes":["Node 8"],"nodeType":0,"enemyType":2,"encounterType":0,"localX":408.23996,"localY":226.421021,"isCurrentNode":false,"color":{"r":1.0,"g":1.0,"b":1.0,"a":1.0}},{"nodeName":"Node 8","isCompleted":false,"connectedNodes":["Node 9","SecondNode 19"],"nodeType":0,"enemyType":0,"encounterType":0,"localX":563.759949,"localY":213.558,"isCurrentNode":false,"color":{"r":1.0,"g":1.0,"b":1.0,"a":1.0}},{"nodeName":"Node 9","isCompleted":false,"connectedNodes":["Final Node"],"nodeType":0,"enemyType":5,"encounterType":0,"localX":719.279968,"localY":-73.4023361,"isCurrentNode":false,"color":{"r":1.0,"g":1.0,"b":1.0,"a":1.0}},{"nodeName":"SecondNode 10","isCompleted":false,"connectedNodes":["SecondNode 11"],"nodeType":0,"enemyType":4,"encounterType":0,"localX":-680.399963,"localY":-124.4737,"isCurrentNode":true,"color":{"r":0.0,"g":0.0,"b":0.0,"a":1.0}},{"nodeName":"SecondNode 11","isCompleted":false,"connectedNodes":["SecondNode 12"],"nodeType":0,"enemyType":4,"encounterType":0,"localX":-524.879944,"localY":-97.42712,"isCurrentNode":false,"color":{"r":0.270588249,"g":0.270588249,"b":0.270588249,"a":1.0}},{"nodeName":"SecondNode 12","isCompleted":false,"connectedNodes":["SecondNode 13"],"nodeType":0,"enemyType":2,"encounterType":0,"localX":-369.36,"localY":259.056976,"isCurrentNode":false,"color":{"r":0.270588249,"g":0.270588249,"b":0.270588249,"a":1.0}},{"nodeName":"SecondNode 13","isCompleted":false,"connectedNodes":["SecondNode 14"],"nodeType":0,"enemyType":1,"encounterType":0,"localX":-213.84,"localY":157.308731,"isCurrentNode":false,"color":{"r":0.270588249,"g":0.270588249,"b":0.270588249,"a":1.0}},{"nodeName":"SecondNode 14","isCompleted":false,"connectedNodes":["SecondNode 15"],"nodeType":0,"enemyType":5,"encounterType":0,"localX":-58.3199959,"localY":68.46584,"isCurrentNode":false,"color":{"r":0.270588249,"g":0.270588249,"b":0.270588249,"a":1.0}},{"nodeName":"SecondNode 15","isCompleted":false,"connectedNodes":["SecondNode 16"],"nodeType":0,"enemyType":0,"encounterType":0,"localX":97.19999,"localY":81.44988,"isCurrentNode":false,"color":{"r":0.270588249,"g":0.270588249,"b":0.270588249,"a":1.0}},{"nodeName":"SecondNode 16","isCompleted":false,"connectedNodes":["SecondNode 17"],"nodeType":0,"enemyType":1,"encounterType":0,"localX":252.719986,"localY":54.5918961,"isCurrentNode":false,"color":{"r":0.270588249,"g":0.270588249,"b":0.270588249,"a":1.0}},{"nodeName":"SecondNode 17","isCompleted":false,"connectedNodes":["SecondNode 18"],"nodeType":0,"enemyType":4,"encounterType":0,"localX":408.23996,"localY":-71.50261,"isCurrentNode":false,"color":{"r":0.270588249,"g":0.270588249,"b":0.270588249,"a":1.0}},{"nodeName":"SecondNode 18","isCompleted":false,"connectedNodes":["SecondNode 19","EncounterSecond Path Node8"],"nodeType":0,"enemyType":2,"encounterType":0,"localX":563.759949,"localY":-178.790756,"isCurrentNode":false,"color":{"r":0.270588249,"g":0.270588249,"b":0.270588249,"a":1.0}},{"nodeName":"SecondNode 19","isCompleted":false,"connectedNodes":["Final Node"],"nodeType":0,"enemyType":0,"encounterType":0,"localX":719.279968,"localY":193.714172,"isCurrentNode":false,"color":{"r":0.270588249,"g":0.270588249,"b":0.270588249,"a":1.0}},{"nodeName":"EncounterFirst Path Node5","isCompleted":false,"connectedNodes":[],"nodeType":2,"enemyType":0,"encounterType":1,"localX":97.33497,"localY":-342.9074,"isCurrentNode":false,"color":{"r":1.0,"g":1.0,"b":1.0,"a":1.0}},{"nodeName":"EncounterSecond Path Node8","isCompleted":false,"connectedNodes":[],"nodeType":2,"enemyType":0,"encounterType":1,"localX":544.8869,"localY":-351.5908,"isCurrentNode":false,"color":{"r":0.270588249,"g":0.270588249,"b":0.270588249,"a":1.0}},{"nodeName":"Final Node","isCompleted":false,"connectedNodes":[],"nodeType":3,"enemyType":7,"encounterType":0,"localX":874.7999,"localY":0.0,"isCurrentNode":false,"color":{"r":1.0,"g":1.0,"b":1.0,"a":1.0}}]}