{"Player":{"coins":6,"blood":6,"pieces":[{"name":"Walthard","uniqueId":0,"pieceType":3,"attack":1,"defense":1,"support":2,"color":0,"posX":4,"posY":0,"abilities":[]},{"name":"Baldo","uniqueId":0,"pieceType":1,"attack":1,"defense":1,"support":1,"color":0,"posX":1,"posY":0,"abilities":[{"abilityName":"General <sprite=\"WhiteKnight\" name=\"WhiteKnight\"> ","abilityDescription":"+1 to all knights, bonus increases for each knight added"}]},{"name":"Sigbod","uniqueId":0,"pieceType":2,"attack":2,"defense":2,"support":1,"color":0,"posX":2,"posY":0,"abilities":[{"abilityName":"Vampire","abilityDescription":"+1 to all stats on dark squares, -1 to all stats on light squares. transfer ability when attacking"},{"abilityName":"Pope <sprite=\"WhiteBishop\" name=\"WhiteBishop\">","abilityDescription":"+1 to all bishops, bonus increases for each bishop added"}]},{"name":"Poma","uniqueId":0,"pieceType":4,"attack":2,"defense":2,"support":2,"color":0,"posX":3,"posY":0,"abilities":[]},{"name":"Alaric","uniqueId":0,"pieceType":5,"attack":1,"defense":1,"support":1,"color":0,"posX":0,"posY":0,"abilities":[]},{"name":"Germaine","uniqueId":0,"pieceType":2,"attack":1,"defense":1,"support":1,"color":0,"posX":6,"posY":1,"abilities":[{"abilityName":"Pickpocket","abilityDescription":"+3 coins when bounced"},{"abilityName":"Pickpocket","abilityDescription":"+3 coins when bounced"}]},{"name":"Siclefrid","uniqueId":0,"pieceType":1,"attack":2,"defense":3,"support":1,"color":0,"posX":6,"posY":0,"abilities":[{"abilityName":"Support Breaker","abilityDescription":"When bounced, reduce all supporting enemies support by -1"},{"abilityName":"Paralyzing Blow","abilityDescription":"When bounced, prevents the defender from moving next turn"}]},{"name":"Valentine","uniqueId":0,"pieceType":3,"attack":1,"defense":1,"support":1,"color":0,"posX":7,"posY":0,"abilities":[{"abilityName":"Betrayer","abilityDescription":"Can capture it's own pieces, supports as if it were an enemy"}]},{"name":"Leah","uniqueId":0,"pieceType":0,"attack":2,"defense":2,"support":2,"color":0,"posX":0,"posY":1,"abilities":[]},{"name":"Gudlogh","uniqueId":0,"pieceType":0,"attack":2,"defense":2,"support":2,"color":0,"posX":1,"posY":1,"abilities":[]},{"name":"Theodegarde","uniqueId":0,"pieceType":0,"attack":2,"defense":2,"support":2,"color":0,"posX":3,"posY":1,"abilities":[{"abilityName":"Scout <sprite=\"WhitePawn\" name=\"WhitePawn\">","abilityDescription":"Moves like queen, attacks & supports like pawn"}]},{"name":"Agulf","uniqueId":0,"pieceType":0,"attack":2,"defense":2,"support":2,"color":0,"posX":4,"posY":2,"abilities":[{"abilityName":"Countermarch <sprite=\"WhitePawn\" name=\"WhitePawn\">","abilityDescription":"Can move and support backwards"}]},{"name":"Bera","uniqueId":0,"pieceType":0,"attack":2,"defense":2,"support":2,"color":0,"posX":6,"posY":2,"abilities":[]},{"name":"Gismunda","uniqueId":0,"pieceType":0,"attack":2,"defense":2,"support":2,"color":0,"posX":7,"posY":1,"abilities":[]},{"name":"Eustace","uniqueId":0,"pieceType":0,"attack":2,"defense":2,"support":2,"color":0,"posX":2,"posY":1,"abilities":[]},{"name":"Warrich","uniqueId":0,"pieceType":2,"attack":4,"defense":3,"support":1,"color":0,"posX":7,"posY":2,"abilities":[{"abilityName":"Critical Blow","abilityDescription":"10% chance of x2 attack"}]},{"name":"Cadwgan","uniqueId":0,"pieceType":2,"attack":1,"defense":1,"support":1,"color":0,"posX":5,"posY":0,"abilities":[]},{"name":"Baldrad","uniqueId":0,"pieceType":1,"attack":1,"defense":1,"support":1,"color":0,"posX":0,"posY":2,"abilities":[]},{"name":"Meinberga","uniqueId":0,"pieceType":7,"attack":2,"defense":2,"support":2,"color":0,"posX":5,"posY":1,"abilities":[{"abilityName":"Longshot","abilityDescription":"+5 attack if attacking from 4 or more squares away"},{"abilityName":"Vampire","abilityDescription":"+1 to all stats on dark squares, -1 to all stats on light squares. transfer ability when attacking"}]}]},"State":3,"Level":6,"MapNodes":[{"nodeName":"Start Node","isCompleted":false,"connectedNodes":["Node 0","SecondNode 10"],"nodeType":0,"enemyType":0,"encounterType":0,"localX":-835.92,"localY":0.0,"isCurrentNode":false,"color":{"r":1.0,"g":1.0,"b":1.0,"a":1.0}},{"nodeName":"Node 0","isCompleted":false,"connectedNodes":["Node 1"],"nodeType":0,"enemyType":0,"encounterType":0,"localX":-680.399963,"localY":-51.6635666,"isCurrentNode":false,"color":{"r":1.0,"g":1.0,"b":1.0,"a":1.0}},{"nodeName":"Node 1","isCompleted":false,"connectedNodes":["Node 2"],"nodeType":0,"enemyType":3,"encounterType":0,"localX":-524.879944,"localY":14.95568,"isCurrentNode":false,"color":{"r":1.0,"g":1.0,"b":1.0,"a":1.0}},{"nodeName":"Node 2","isCompleted":false,"connectedNodes":["Node 3","SecondNode 13"],"nodeType":0,"enemyType":2,"encounterType":0,"localX":-369.36,"localY":-95.506485,"isCurrentNode":false,"color":{"r":1.0,"g":1.0,"b":1.0,"a":1.0}},{"nodeName":"Node 3","isCompleted":false,"connectedNodes":["Node 4"],"nodeType":0,"enemyType":2,"encounterType":0,"localX":-213.84,"localY":-5.897444,"isCurrentNode":false,"color":{"r":1.0,"g":1.0,"b":1.0,"a":1.0}},{"nodeName":"Node 4","isCompleted":false,"connectedNodes":["Node 5"],"nodeType":0,"enemyType":3,"encounterType":0,"localX":-58.3199959,"localY":3.30359745,"isCurrentNode":false,"color":{"r":1.0,"g":1.0,"b":1.0,"a":1.0}},{"nodeName":"Node 5","isCompleted":false,"connectedNodes":["Node 6"],"nodeType":0,"enemyType":3,"encounterType":0,"localX":97.19999,"localY":-130.743881,"isCurrentNode":false,"color":{"r":1.0,"g":1.0,"b":1.0,"a":1.0}},{"nodeName":"Node 6","isCompleted":false,"connectedNodes":["Node 7"],"nodeType":0,"enemyType":1,"encounterType":0,"localX":252.719986,"localY":146.34729,"isCurrentNode":false,"color":{"r":1.0,"g":1.0,"b":1.0,"a":1.0}},{"nodeName":"Node 7","isCompleted":false,"connectedNodes":["Node 8"],"nodeType":0,"enemyType":6,"encounterType":0,"localX":408.23996,"localY":191.819534,"isCurrentNode":false,"color":{"r":1.0,"g":1.0,"b":1.0,"a":1.0}},{"nodeName":"Node 8","isCompleted":false,"connectedNodes":["Node 9"],"nodeType":0,"enemyType":6,"encounterType":0,"localX":563.759949,"localY":-223.5803,"isCurrentNode":false,"color":{"r":1.0,"g":1.0,"b":1.0,"a":1.0}},{"nodeName":"Node 9","isCompleted":false,"connectedNodes":["Final Node","EncounterFirst Path Node9"],"nodeType":0,"enemyType":0,"encounterType":0,"localX":719.279968,"localY":139.0365,"isCurrentNode":false,"color":{"r":1.0,"g":1.0,"b":1.0,"a":1.0}},{"nodeName":"SecondNode 10","isCompleted":false,"connectedNodes":["SecondNode 11","Node 1"],"nodeType":0,"enemyType":2,"encounterType":0,"localX":-680.399963,"localY":-246.023834,"isCurrentNode":false,"color":{"r":0.0,"g":0.0,"b":0.0,"a":1.0}},{"nodeName":"SecondNode 11","isCompleted":false,"connectedNodes":["SecondNode 12"],"nodeType":0,"enemyType":5,"encounterType":0,"localX":-524.879944,"localY":218.720551,"isCurrentNode":false,"color":{"r":0.0,"g":0.0,"b":0.0,"a":1.0}},{"nodeName":"SecondNode 12","isCompleted":false,"connectedNodes":["SecondNode 13"],"nodeType":0,"enemyType":0,"encounterType":0,"localX":-369.36,"localY":241.239883,"isCurrentNode":false,"color":{"r":0.0,"g":0.0,"b":0.0,"a":1.0}},{"nodeName":"SecondNode 13","isCompleted":false,"connectedNodes":["SecondNode 14"],"nodeType":0,"enemyType":2,"encounterType":0,"localX":-213.84,"localY":-179.233215,"isCurrentNode":false,"color":{"r":0.0,"g":0.0,"b":0.0,"a":1.0}},{"nodeName":"SecondNode 14","isCompleted":false,"connectedNodes":["SecondNode 15"],"nodeType":0,"enemyType":4,"encounterType":0,"localX":-58.3199959,"localY":245.663269,"isCurrentNode":true,"color":{"r":0.0,"g":0.0,"b":0.0,"a":1.0}},{"nodeName":"SecondNode 15","isCompleted":false,"connectedNodes":["SecondNode 16","EncounterSecond Path Node5"],"nodeType":0,"enemyType":6,"encounterType":0,"localX":97.19999,"localY":74.5060349,"isCurrentNode":false,"color":{"r":0.270588249,"g":0.270588249,"b":0.270588249,"a":1.0}},{"nodeName":"SecondNode 16","isCompleted":false,"connectedNodes":["SecondNode 17","Node 7"],"nodeType":0,"enemyType":2,"encounterType":0,"localX":252.719986,"localY":-144.641739,"isCurrentNode":false,"color":{"r":0.270588249,"g":0.270588249,"b":0.270588249,"a":1.0}},{"nodeName":"SecondNode 17","isCompleted":false,"connectedNodes":["SecondNode 18"],"nodeType":0,"enemyType":1,"encounterType":0,"localX":408.23996,"localY":-102.088623,"isCurrentNode":false,"color":{"r":0.270588249,"g":0.270588249,"b":0.270588249,"a":1.0}},{"nodeName":"SecondNode 18","isCompleted":false,"connectedNodes":["SecondNode 19"],"nodeType":0,"enemyType":0,"encounterType":0,"localX":563.759949,"localY":130.401581,"isCurrentNode":false,"color":{"r":0.270588249,"g":0.270588249,"b":0.270588249,"a":1.0}},{"nodeName":"SecondNode 19","isCompleted":false,"connectedNodes":["Final Node"],"nodeType":0,"enemyType":0,"encounterType":0,"localX":719.279968,"localY":-84.2374,"isCurrentNode":false,"color":{"r":0.270588249,"g":0.270588249,"b":0.270588249,"a":1.0}},{"nodeName":"EncounterFirst Path Node9","isCompleted":false,"connectedNodes":[],"nodeType":2,"enemyType":0,"encounterType":1,"localX":726.6143,"localY":311.836548,"isCurrentNode":false,"color":{"r":1.0,"g":1.0,"b":1.0,"a":1.0}},{"nodeName":"EncounterSecond Path Node5","isCompleted":false,"connectedNodes":[],"nodeType":2,"enemyType":0,"encounterType":1,"localX":87.05227,"localY":247.306061,"isCurrentNode":false,"color":{"r":0.270588249,"g":0.270588249,"b":0.270588249,"a":1.0}},{"nodeName":"Final Node","isCompleted":false,"connectedNodes":[],"nodeType":3,"enemyType":7,"encounterType":0,"localX":874.7999,"localY":0.0,"isCurrentNode":false,"color":{"r":1.0,"g":1.0,"b":1.0,"a":1.0}}]}